[
  {
    "file": "./journal/je_001.html",
    "image": "https://placehold.co/1600x900/png",
    "date": "01.06.2024",
    "title": "Test 001",
    "caption": "Test caption Template"
  },
  {
    "file": "./journal/je_002.html",
    "image": "https://placehold.co/1600x900/png",
    "date": "03.12.2023",
    "title": "Test 002",
    "caption": "Test caption Template"
  },
  {
    "file": "./journal/je_003.html",
    "image": "https://placehold.co/1600x900/png",
    "date": "22.01.2022",
    "title": "Test 003",
    "caption": "Test caption Template"
  },
  {
    "file": "./journal/je_004.html",
    "image": "https://placehold.co/1600x900/png",
    "date": "22.01.2022",
    "title": "Test 004",
    "caption": "Test caption Template"
  },
    {
    "file": "./journal/je_005.html",
    "image": "https://placehold.co/1600x900/png",
    "date": "22.01.2022",
    "title": "Test 005",
    "caption": "Test caption Template"
  },
    {
    "file": "./journal/je_006.html",
    "image": "https://placehold.co/1600x900/png",
    "date": "22.01.2022",
    "title": "Website & J+S",
    "caption": "Test caption Template"
  },
    {
    "file": "./journal/je_007.html",
    "image": "https://placehold.co/1600x900/png",
    "date": "22.01.2022",
    "title": "Mid-season 25/26 pulse",
    "caption": "Test caption Template"
  }
]
